setup.py
pydistro/Binomialdistribution.py
pydistro/Gaussiandistribution.py
pydistro/Generaldistribution.py
pydistro/__init__.py
pydistro.egg-info/PKG-INFO
pydistro.egg-info/SOURCES.txt
pydistro.egg-info/dependency_links.txt
pydistro.egg-info/not-zip-safe
pydistro.egg-info/top_level.txt