Metadata-Version: 1.0
Name: pydistro
Version: 0.1
Summary: Gaussian distributions
Home-page: UNKNOWN
Author: Praful Mohanan
Author-email: praful.mohanan@gmail.com
License: UNKNOWN
Platform: UNKNOWN
